async_fifo/dualport_ram_async.v
module dualport_ram_async #(
		parameter	DATA_WIDTH = 8,
		parameter	ADDR_WIDTH = 4  //ram depth is equal to 2^ADDR_WIDTH
		)(
		input wr_clk,
		input wr_rst_n,
		input wr_en,
		input [ADDR_WIDTH-1:0] wr_addr,
		input [DATA_WIDTH-1:0] wr_data,
		input rd_clk,
		input rd_rst_n,
		input rd_en,
		input [ADDR_WIDTH-1:0] rd_addr,
		output reg [DATA_WIDTH-1:0] rd_data
    );

    localparam 	RAM_DEPTH = 1<<ADDR_WIDTH;

    reg [DATA_WIDTH-1:0] mem [RAM_DEPTH-1:0];
    integer II;
    always @(posedge wr_clk or negedge wr_rst_n) begin
            if(!wr_rst_n) begin
                for(II=0;II<RAM_DEPTH;II=II+1) begin
                    mem[II] <= {DATA_WIDTH{1'b0}};
                end 
            end
            else if(wr_en) begin
                mem[wr_addr] <= wr_data;
            end
    end

    always @(posedge rd_clk or negedge rd_rst_n) begin
        if(!rd_rst_n) begin
            rd_data <= {DATA_WIDTH{1'b0}};
        end 
        else if(rd_en) begin
            rd_data = mem[rd_addr];
        end
    end

    //assign rd_data = mem[rd_addr]; //为什么用组合逻辑，而不是时序逻辑

endmodule

.history/async_fifo/async_fifo_20220305221831.v
`include "dualport_ram_async.v" 
module async_fifo #(
  parameter DATA_WIDTH  = 4           ,
  parameter FIFO_DEPTH  = 16          ,
  parameter FIFO_AFULL  = FIFO_DEPTH-1,
  parameter FIFO_AEMPTY = 1
) (
  input                       wr_clk  ,
  input                       wr_rst_n,
  input                       wr_en   ,
  input      [DATA_WIDTH-1:0] wr_data ,
  input                       rd_clk  ,
  input                       rd_rst_n,
  input                       rd_en   ,
  output    [DATA_WIDTH-1:0]  rd_data ,
  output reg                  full    ,
  output  reg                  empty   ,
  output  reg                  afull   ,
  output reg                  aempty
);

localparam ADDR_WIDTH = $clog2(FIFO_DEPTH); //位宽

reg [ADDR_WIDTH:0] rd_addr;
reg [ADDR_WIDTH:0] rd_addr_nxt;

reg [ADDR_WIDTH:0] wr_addr;
reg [ADDR_WIDTH:0] wr_addr_nxt;

wire [ADDR_WIDTH:0] wr_addr_gray_nxt;
reg  [ADDR_WIDTH:0] wr_addr_gray;
reg  [ADDR_WIDTH:0] wr_addr_gray_rsyn1;
reg  [ADDR_WIDTH:0] wr_addr_gray_rsyn2;
wire [ADDR_WIDTH:0] wr_addr_gray_rsyn;

wire [ADDR_WIDTH:0] rd_addr_gray_nxt;
reg  [ADDR_WIDTH:0] rd_addr_gray;
reg  [ADDR_WIDTH:0] rd_addr_gray_wsyn1;
reg  [ADDR_WIDTH:0] rd_addr_gray_wsyn2;
wire [ADDR_WIDTH:0] rd_addr_gray_wsyn;

wire [ADDR_WIDTH:0] rd_addr_gray_wsyn_bin;
wire [ADDR_WIDTH:0] fifo_used_wr;
wire [ADDR_WIDTH:0] wr_addr_gray_rsyn_bin;

wire                wr_vld;
wire                rd_vld;

wire                full_comb;
wire                empty_comb;


reg  [ADDR_WIDTH:0] wr_addr_gray_rsyn3;
reg  [ADDR_WIDTH:0] rd_addr_gray_wsyn3;
assign wr_vld = wr_en && ~full;
assign rd_vld = rd_en && ~empty;

dualport_ram_async #(
    .DATA_WIDTH(DATA_WIDTH),
    .ADDR_WIDTH(ADDR_WIDTH)
)dualport_ram_inst(
    .wr_clk (wr_clk),
    .wr_rst_n(wr_rst_n),
    .wr_en(wr_vld),
    .wr_addr(wr_addr[ADDR_WIDTH-1:0]),
    .wr_data(wr_data),
    .rd_clk(rd_clk),
    .rd_rst_n(rd_rst_n),
    .rd_en(rd_vld),
    .rd_addr(rd_addr[ADDR_WIDTH-1:0]),
    .rd_data(rd_data)
    );

always @(*) begin
    if(wr_vld)
        wr_addr_nxt = wr_addr + 1'b1;
    else
        wr_addr_nxt = wr_addr;
end

always @(posedge wr_clk or negedge wr_rst_n) begin
    if(!wr_rst_n)
        wr_addr <= {(ADDR_WIDTH+1){1'b0}};
    else 
        wr_addr <= wr_addr_nxt;
end

always @(*) begin
    if(rd_vld)
        rd_addr_nxt = rd_addr +1'b1;
    else
        rd_addr_nxt = rd_addr;
end

always @(posedge rd_clk or negedge rd_rst_n) begin
    if(!rd_rst_n)
        rd_addr <= {(ADDR_WIDTH+1){1'b0}};
    else 
        rd_addr <= rd_addr_nxt;
end

assign wr_addr_gray_nxt = (wr_addr_nxt>>1) ^ wr_addr_nxt;

always @(posedge wr_clk or negedge wr_rst_n) begin
   if(!wr_rst_n)    begin
     wr_addr_gray <={(ADDR_WIDTH+1){1'b0}};   
   end
   else
     wr_addr_gray <= wr_addr_gray_nxt;
end

assign rd_addr_gray_nxt = (rd_addr_nxt>>1) ^ rd_addr_nxt;

always @(posedge rd_clk or negedge rd_rst_n) begin
    if(!rd_rst_n)    begin
      rd_addr_gray <={(ADDR_WIDTH+1){1'b0}};   
    end
    else
      rd_addr_gray <= rd_addr_gray_nxt;
 end

 always @(posedge wr_clk or negedge wr_rst_n) begin
     if(!wr_rst_n)begin
        rd_addr_gray_wsyn1 <= {(ADDR_WIDTH+1){1'b0}};
        rd_addr_gray_wsyn2 <= {(ADDR_WIDTH+1){1'b0}};
     end
     else begin
       rd_addr_gray_wsyn1 <= rd_addr_gray;
       rd_addr_gray_wsyn2 <= rd_addr_gray_wsyn1;
     end
 end

 always @(posedge rd_clk or negedge rd_rst_n) begin
    if(!wr_rst_n)begin
       wr_addr_gray_rsyn1 <= {(ADDR_WIDTH+1){1'b0}};
       wr_addr_gray_rsyn2 <= {(ADDR_WIDTH+1){1'b0}};
    end
    else begin
      wr_addr_gray_wsyn1 <= wr_addr_gray;
      wr_addr_gray_wsyn2 <= wr_addr_gray_wsyn1;
    end
end

assign wr_addr_gray_rsyn = wr_addr_gray_rsyn2;
assign rd_addr_gray_wsyn = rd_addr_gray_wsyn2;

assign full_comb = (wr_addr_gray_nxt == {~rd_addr_gray_wsyn[ADDR_WIDTH:ADDR_WIDTH-1],rd_addr_gray_wsyn[ADDR_WIDTH-2:0]});

always @(posedge wr_clk or negedge wr_rst_n) begin
    if(!wr_rst_n)
        full <= 1'b0;
    else 
        full <= full_comb;
end

assign empty_comb = rd_addr_gray_nxt == wr_addr_gray_rsyn;
always @(posedge rd_clk or rd_rst_n) begin
    if(!rd_rst_n)
        empty <= 1'b0;
    else
        empty <= empty_comb;
end
//????
generate
genvar i;
    for(i=ADDR_WIDTH;i>=0;i=i-1)
        begin
          if(i == ADDR_WIDTH)
            assign rd_addr_gray_wsyn_bin[i] = rd_addr_gray_wsyn[i];
        else
            assign rd_addr_gray_wsyn_bin[i] = rd_addr_gray_wsyn[i]^rd_addr_gray_wsyn[i+1];
        end
endgenerate

assign fifo_used_wr = wr_addr_nxt - rd_addr_gray_wsyn_bin;

wire afull_comb;
assign afull_comb = (fifo_used_wr>=FIFO_AFULL);

always @ (posedge wr_clk or negedge wr_rst_n)
begin
	if(!wr_rst_n)
		afull <= 1'b0;
	else
		afull <= afull_comb;
end 


wire [ADDR_WIDTH:0] fifo_used_rd;
assign fifo_used_rd = wr_addr_gray_rsyn_bin - rd_addr_nxt;

wire aempty_comb;
assign aempty_comb = (fifo_used_rd<=FIFO_AEMPTY);

always @ (posedge rd_clk or negedge rd_rst_n)
begin
	if(!rd_rst_n)
		aempty <= 1'b1;
	else
		aempty <= aempty_comb;
end 
endmodule

async_fifo/async_fifo_tb.v
`include "async_fifo.v"
module async_fifo_tb;

  // Parameters
  localparam  DATA_WIDTH = 4;
  localparam  FIFO_DEPTH = 8;
  localparam  FIFO_AFULL = FIFO_DEPTH-1;
  localparam  FIFO_AEMPTY = 1;

  // Ports
  reg wr_clk = 0;
  reg wr_rst_n = 0;
  reg wr_en = 0;
  reg [DATA_WIDTH-1:0] wr_data;
  reg rd_clk = 0;
  reg rd_rst_n = 0;
  reg rd_en = 0;
  wire [DATA_WIDTH-1:0] rd_data;
  wire full;
  wire empty;
  wire afull;
  wire aempty;

  async_fifo 
  #(
    .DATA_WIDTH(DATA_WIDTH ),
    .FIFO_DEPTH(FIFO_DEPTH ),
    .FIFO_AFULL(FIFO_AFULL ),
    .FIFO_AEMPTY (
        FIFO_AEMPTY )
  )
  async_fifo_dut (
    .wr_clk (wr_clk ),
    .wr_rst_n (wr_rst_n ),
    .wr_en (wr_en ),
    .wr_data (wr_data ),
    .rd_clk (rd_clk ),
    .rd_rst_n (rd_rst_n ),
    .rd_en (rd_en ),
    .rd_data (rd_data ),
    .full (full ),
    .empty (empty ),
    .afull (afull ),
    .aempty  ( aempty)
  );

  initial begin
    begin
      wr_rst_n = 0;
      rd_rst_n = 0;
      #50;
      wr_rst_n = 1;
      rd_rst_n = 1;
    end
  end
  initial begin
      #100
      wr_task;
      #100
      rd_task;
      #1000
      $finish;
  end
task wr_task;
begin
    @(posedge wr_clk)
        begin
            wr_en <= 1;
            wr_data <= 8'ha;
        end
        @(posedge wr_clk)
        begin
            wr_en <= 1;
            wr_data <= 8'hb;
        end
        @(posedge wr_clk)
        begin
            wr_en <= 1;
            wr_data <= 8'hc;
        end
        @(posedge wr_clk)
        begin
            wr_en <= 1;
            wr_data <= 8'hd;
        end
        @(posedge wr_clk)
        begin
            wr_en <= 1;
            wr_data <= 8'he;
        end
        @(posedge wr_clk)
        begin
            wr_en <= 1;
            wr_data <= 8'hf;
        end
        @(posedge wr_clk)
        begin
            wr_en <= 0;
        end
        @(posedge wr_clk)
        begin
            wr_en <= 1;
            wr_data <= 8'hf;
        end
        @(posedge wr_clk)
        begin
            wr_en <= 1;
            wr_data <= 8'hf;
        end
        @(posedge wr_clk)
        begin
            wr_en <= 1;
            wr_data <= 8'hf;
        end
        @(posedge wr_clk)
        begin
            wr_en <= 1;
            wr_data <= 8'hf;
        end
        @(posedge wr_clk)
        begin
            wr_en <= 1;
            wr_data <= 8'hf;
        end
        @(posedge wr_clk)
        begin
            wr_en <= 1;
            wr_data <= 8'hf;
        end
        @(posedge wr_clk)
        begin
            wr_en <= 1;
            wr_data <= 8'ha;
        end
        @(posedge wr_clk)
        begin
            wr_en <= 1;
            wr_data <= 8'hb;
        end
        @(posedge wr_clk)
        begin
            wr_en <= 0;
        end
end
endtask
task rd_task;
begin
    @(posedge rd_clk)
        rd_en <= 1;
        @(posedge rd_clk)
        rd_en <= 1;
        @(posedge rd_clk)
        rd_en <= 1;
        @(posedge rd_clk)
        rd_en <= 1;
        @(posedge rd_clk)
        rd_en <= 1;
        @(posedge rd_clk)
        rd_en <= 0;
        @(posedge rd_clk)
        rd_en <= 1;
        @(posedge rd_clk)
        rd_en <= 0;
        @(posedge rd_clk)
        rd_en <= 1;
        @(posedge rd_clk)
        rd_en <= 1;
        @(posedge rd_clk)
        rd_en <= 1;
        @(posedge rd_clk)
        rd_en <= 1;
        @(posedge rd_clk)
        rd_en <= 1;
        @(posedge rd_clk)
        rd_en <= 0;
end
endtask


  always
    #5  wr_clk = ! wr_clk ;
  always
    #20  rd_clk = ! rd_clk ;

    /*iverilog */
initial
begin
  $dumpfile("wave.vcd");        //生成的vcd文件名称
  $dumpvars;
end
endmodule

async_fifo/build/wave.vcd
$date
	Sat Mar  5 22:49:00 2022
$end
$version
	Icarus Verilog
$end
$timescale
	1s
$end
$scope module async_fifo_tb $end
$var wire 4 ! rd_data [3:0] $end
$var wire 1 " full $end
$var wire 1 # empty $end
$var wire 1 $ afull $end
$var wire 1 % aempty $end
$var reg 1 & rd_clk $end
$var reg 1 ' rd_en $end
$var reg 1 ( rd_rst_n $end
$var reg 1 ) wr_clk $end
$var reg 4 * wr_data [3:0] $end
$var reg 1 + wr_en $end
$var reg 1 , wr_rst_n $end
$scope module async_fifo_dut $end
$var wire 4 - rd_addr_gray_nxt [3:0] $end
$var wire 1 & rd_clk $end
$var wire 1 ' rd_en $end
$var wire 1 ( rd_rst_n $end
$var wire 1 . rd_vld $end
$var wire 4 / wr_addr_gray_nxt [3:0] $end
$var wire 1 ) wr_clk $end
$var wire 4 0 wr_data [3:0] $end
$var wire 1 + wr_en $end
$var wire 1 , wr_rst_n $end
$var wire 1 1 wr_vld $end
$var wire 4 2 wr_addr_gray_rsyn_bin [3:0] $end
$var wire 4 3 wr_addr_gray_rsyn [3:0] $end
$var wire 4 4 rd_data [3:0] $end
$var wire 4 5 rd_addr_gray_wsyn_bin [3:0] $end
$var wire 4 6 rd_addr_gray_wsyn [3:0] $end
$var wire 1 7 full_comb $end
$var wire 4 8 fifo_used_wr [3:0] $end
$var wire 4 9 fifo_used_rd [3:0] $end
$var wire 1 : empty_comb $end
$var wire 1 ; afull_comb $end
$var wire 1 < aempty_comb $end
$var reg 1 % aempty $end
$var reg 1 $ afull $end
$var reg 1 # empty $end
$var reg 1 " full $end
$var reg 4 = rd_addr [3:0] $end
$var reg 4 > rd_addr_gray [3:0] $end
$var reg 4 ? rd_addr_gray_wsyn1 [3:0] $end
$var reg 4 @ rd_addr_gray_wsyn2 [3:0] $end
$var reg 4 A rd_addr_nxt [3:0] $end
$var reg 4 B wr_addr [3:0] $end
$var reg 4 C wr_addr_gray [3:0] $end
$var reg 4 D wr_addr_gray_rsyn1 [3:0] $end
$var reg 4 E wr_addr_gray_rsyn2 [3:0] $end
$var reg 4 F wr_addr_nxt [3:0] $end
$scope begin genblk1[0] $end
$scope begin genblk3 $end
$upscope $end
$upscope $end
$scope begin genblk1[1] $end
$scope begin genblk3 $end
$upscope $end
$upscope $end
$scope begin genblk1[2] $end
$scope begin genblk3 $end
$upscope $end
$upscope $end
$scope begin genblk1[3] $end
$scope begin genblk2 $end
$upscope $end
$upscope $end
$scope begin genblk4[0] $end
$scope begin genblk6 $end
$upscope $end
$upscope $end
$scope begin genblk4[1] $end
$scope begin genblk6 $end
$upscope $end
$upscope $end
$scope begin genblk4[2] $end
$scope begin genblk6 $end
$upscope $end
$upscope $end
$scope begin genblk4[3] $end
$scope begin genblk5 $end
$upscope $end
$upscope $end
$scope module dualport_ram_inst $end
$var wire 3 G rd_addr [2:0] $end
$var wire 1 & rd_clk $end
$var wire 1 . rd_en $end
$var wire 1 ( rd_rst_n $end
$var wire 3 H wr_addr [2:0] $end
$var wire 1 ) wr_clk $end
$var wire 4 I wr_data [3:0] $end
$var wire 1 1 wr_en $end
$var wire 1 , wr_rst_n $end
$var reg 4 J rd_data [3:0] $end
$var integer 32 K II [31:0] $end
$upscope $end
$upscope $end
$scope task rd_task $end
$upscope $end
$scope task wr_task $end
$upscope $end
$upscope $end
$enddefinitions $end
#0
$dumpvars
b1000 K
b0 J
bx I
b0 H
b0 G
b0 F
b0 E
b0 D
b0 C
b0 B
b0 A
b0 @
b0 ?
b0 >
b0 =
1<
0;
1:
b0 9
b0 8
07
b0 6
b0 5
b0 4
b0 3
b0 2
01
bx 0
b0 /
0.
b0 -
0,
0+
bx *
0)
0(
0'
0&
0%
0$
0#
0"
b0 !
$end
#5
b1000 K
1)
#10
0)
#15
b1000 K
1)
#20
0)
1&
#25
b1000 K
1)
#30
0)
#35
b1000 K
1)
#40
0)
0&
#45
b1000 K
1)
#50
1#
0)
1(
1,
#55
1)
#60
1%
0)
1&
#65
1)
#70
0)
#75
1)
#80
0)
0&
#85
1)
#90
0)
#95
1)
#100
0)
1&
#105
b1 /
b1 8
b1 F
11
b1010 *
b1010 0
b1010 I
1+
1)
#110
0)
#115
b11 /
b10 8
b10 F
b1 H
b1 B
b1 C
b1011 *
b1011 0
b1011 I
1)
#120
0)
0&
#125
b10 /
b11 8
b11 F
b10 H
b11 C
b10 B
b1100 *
b1100 0
b1100 I
1)
#130
0)
#135
b110 /
b100 8
b100 F
b11 H
b11 B
b10 C
b1101 *
b1101 0
b1101 I
1)
#140
b10 D
0)
1&
#145
b111 /
b101 8
b101 F
b100 H
b110 C
b100 B
b1110 *
b1110 0
b1110 I
1)
#150
0)
#155
b101 /
b110 8
b110 F
b101 H
b101 B
b111 C
b1111 *
b1111 0
b1111 I
1)
#160
0)
0&
#165
b110 H
01
b101 C
b110 B
0+
1)
#170
0)
#175
b100 /
1;
b111 8
b111 F
11
1+
1)
#180
0<
b11 9
b11 2
0:
b10 3
b10 E
b101 D
0)
1&
#185
17
b1100 /
b1000 8
b1000 F
b111 H
1$
b100 C
b111 B
1)
#190
0)
#195
17
b1100 /
01
b1000 8
b1000 F
b0 H
b1000 B
b1100 C
1"
1)
#200
0)
0&
#205
1)
#210
0)
#215
1)
#220
b111 9
b111 2
b101 3
b101 E
b1100 D
0%
0#
0)
1&
#225
1)
#230
0)
#235
b1010 *
b1010 0
b1010 I
1)
#240
0)
0&
#245
b1011 *
b1011 0
b1011 I
1)
#250
0)
#255
0+
1)
#260
b1010 9
b1010 2
b1100 3
b1100 E
0)
1&
#265
1)
#270
0)
#275
1)
#280
0)
0&
#285
1)
#290
0)
#295
1)
#300
0)
1&
#305
1)
#310
0)
#315
1)
#320
0)
0&
#325
1)
#330
0)
#335
1)
#340
0)
1&
#345
1)
#350
0)
#355
1)
#360
0)
0&
#365
1)
#370
0)
#375
1)
#380
b1 -
b1001 9
b1 A
1.
1'
0)
1&
#385
1)
#390
0)
#395
1)
#400
0)
0&
#405
1)
#410
0)
#415
1)
#420
b11 -
b1000 9
b10 A
b1 G
b1 >
b1 =
b1010 !
b1010 4
b1010 J
0)
1&
#425
b1 ?
1)
#430
0)
#435
b111 8
b1 5
07
b1 6
b1 @
1)
#440
0)
0&
#445
0"
1)
#450
0)
#455
1)
#460
b10 -
b111 9
b11 A
b10 G
b10 =
b11 >
b1011 !
b1011 4
b1011 J
0)
1&
#465
b11 ?
1)
#470
0)
#475
0;
b110 8
b10 5
b11 6
b11 @
1)
#480
0)
0&
#485
0$
1)
#490
0)
#495
1)
#500
b110 -
b110 9
b100 A
b11 G
b10 >
b11 =
b1100 !
b1100 4
b1100 J
0)
1&
#505
b10 ?
1)
#510
0)
#515
b101 8
b11 5
b10 6
b10 @
1)
#520
0)
0&
#525
1)
#530
0)
#535
1)
#540
b111 -
b101 9
b101 A
b100 G
b100 =
b110 >
b1101 !
b1101 4
b1101 J
0)
1&
#545
b110 ?
1)
#550
0)
#555
0;
b11 8
b101 5
b110 6
b110 @
1)
#560
0)
0&
#565
1)
#570
0)
#575
1)
#580
b101 G
0.
b111 >
b101 =
0'
b1110 !
b1110 4
b1110 J
0)
1&
#585
b111 ?
1)
#590
0)
#595
b100 8
b100 5
b111 6
b111 @
1)
#600
0)
0&
#605
1)
#610
0)
#615
1)
#620
b101 -
b100 9
b110 A
1.
1'
0)
1&
#625
1)
#630
0)
#635
1)
#640
0)
0&
#645
1)
#650
0)
#655
1)
#660
b110 G
0.
b101 >
b110 =
0'
b1111 !
b1111 4
b1111 J
0)
1&
#665
b101 ?
1)
#670
0)
#675
b1 8
b111 5
b101 6
b101 @
1)
#680
0)
0&
#685
1)
#690
0)
#695
1)
#700
b100 -
b11 9
b111 A
1.
1'
0)
1&
#705
1)
#710
0)
#715
1)
#720
0)
0&
#725
1)
#730
0)
#735
1)
#740
1:
b1100 -
b10 9
b1000 A
b111 G
b100 >
b111 =
0)
1&
#745
b100 ?
1)
#750
0)
#755
b10 8
b110 5
b100 6
b100 @
1)
#760
0)
0&
#765
1)
#770
0)
#775
1)
#780
1:
b1100 -
0.
0<
b10 9
b1000 A
b0 G
b1000 =
b1100 >
1#
0)
1&
#785
b1100 ?
1)
#790
0)
#795
1;
b1110 8
b1010 5
b1100 6
b1100 @
1)
#800
0)
0&
#805
1$
1)
#810
0)
#815
1)
#820
0)
1&
#825
1)
#830
0)
#835
1)
#840
0)
0&
#845
1)
#850
0)
#855
1)
#860
0)
1&
#865
1)
#870
0)
#875
1)
#880
0)
0&
#885
1)
#890
0)
#895
1)
#900
0'
0)
1&
