SPI/SPI.v
module SPI #(
  parameter CMD_WIDTH  = 12,
  parameter READ_WIDTH = 8
) (
  input                   clk      ,
  input                   rst_n    ,
  input  [ CMD_WIDTH-1:0] cmd_in   ,
  output      reg         cmd_rdy  ,
  input                   cmd_vld  ,
  output      reg            sclk     ,
  output      reg            cs       ,
  output      reg            mosi     ,
  input                   miso     ,
  output       reg           read_vld ,
  output reg [READ_WIDTH-1:0] read_data
);
reg [3:0] fsm_cs;
reg [3:0] fsm_ns;
reg [CMD_WIDTH-1:0] buff;
wire work_en;
wire w_start_en;
wire w_start_down;
reg [3:0] w_cnt;
reg [3:0] r_cnt;
wire r_start_en;
wire r_start_down;
reg [3:0] clk_cnt;
reg [7:0] dly_cnt;
reg [7:0] data_buf;
reg [3:0] rbuff;
localparam IDLE     = 4'd0,
           START    = 4'd1,
           JUDGE    = 4'd2,
           W_START  = 4'd3,
           W_DATA   = 4'd4,
           W_FINISH = 4'd5,
           R_START  = 4'd6,
           WR_DATA  = 4'd7,
           R_DELAY  = 4'd8,
           RR_DATA  = 4'd9, 
           R_FINISH = 4'd10;
// localparam DATA_WIDTH = 1,
//            FIFO_DEPTH = 8,
//            FIFO_AFULL = 1,
//            FIFO_AEMPTY = 1;
always @(posedge clk or negedge rst_n) begin
    if(!rst_n)
        fsm_cs <= IDLE;
    else
        fsm_cs <= fsm_ns;
end

assign work_en = cmd_vld;

always @(*) begin
    case(fsm_ns)
        IDLE    :
        begin
            if(work_en)
                fsm_ns = START;
            else
                fsm_ns = IDLE;
        end  
        START   :
        begin
            if(cmd_vld)
                fsm_ns = JUDGE;
            else
                fsm_ns = START;
        end 
        JUDGE   :
        begin
            if(buff[11] == 1 && cmd_vld)
                fsm_ns = W_START;
            else if(buff[11] == 0)
                fsm_ns = R_START;
            else
                fsm_ns = JUDGE;
        end
        W_START :
        begin
            if(w_start_en)
                fsm_ns = W_DATA;
            else
                fsm_ns = W_START;
        end
        W_DATA  :
        begin
            if(w_cnt == 4'd12 && clk_cnt == 4'd10)
                fsm_ns = W_FINISH;
            else
                fsm_ns = W_DATA;
        end
        W_FINISH :
        begin
            if(w_start_down)
                fsm_ns = IDLE;
            else
                fsm_ns = W_FINISH;
        end
        R_START :
        begin
            if(r_start_en)
                fsm_ns = WR_DATA;
            else
                fsm_ns = R_START;
        end
        WR_DATA :
        begin
            if(r_cnt == 4'd4)
                fsm_ns = R_DELAY;
            else
                fsm_ns = WR_DATA;
        end
        R_DELAY :
        begin
            if(dly_cnt == 8'd100)
                fsm_ns = RR_DATA;
            else
                fsm_ns = R_DELAY;
        end
        RR_DATA :
        begin
            if(r_cnt == 4'd8)
                fsm_ns = R_FINISH;
            else
                fsm_ns = RR_DATA;
        end
        R_FINISH :
        begin
          if(r_start_down)
            fsm_ns = IDLE;
        else
            fsm_ns = R_FINISH;
        end
        default:
            fsm_ns = IDLE;
    endcase
end

assign w_start_en = buff[11] && ~cmd_rdy;
assign w_start_down = w_cnt == 4'd12;
assign r_start_en = ~buff[11] && ~cmd_rdy;
assign r_start_down = w_cnt == 4'd8;
always @(posedge clk or negedge rst_n) begin
    case (fsm_cs)
        IDLE   :
            begin
              w_cnt <= 4'b0;
              r_cnt <= 4'b0;
              buff <= 12'b0;
              clk_cnt <= 4'b0;
              dly_cnt <= 8'b0;
              data_buf <= 8'b0;
              rbuff <= 4'b0;
              cmd_rdy <= 1'b1;
              sclk <= 1'b0;
              cs <= 1'b1;
              mosi <= 1'b0;
              read_vld <= 1'b0;
              read_data <= 8'b0;

            end 
        START  :
            begin
              buff <= cmd_in;
              cmd_rdy <= 1'b0;    
            end
        JUDGE  :
            begin
              cmd_rdy <= 1'b0;  
            end
        W_START :
            ;
        W_DATA  :
        begin
            cs <= 1'b0;
            mosi <= buff[w_cnt];
            if(clk_cnt == 4'd10)  
              begin
                clk_cnt <= 4'd1; 
                sclk <= ~sclk;
              end
            else if(clk_cnt == 4'd5)
            begin
                sclk <= ~sclk;
                clk_cnt <= clk_cnt + 1'b1;
            end
            else if(clk_cnt == 4'd9)
              begin
                w_cnt <= w_cnt + 1'b1;
                clk_cnt <= clk_cnt + 1'b1;        
              end
            else
                clk_cnt <= clk_cnt + 1'b1;    
            if(w_cnt == 4'd12 && clk_cnt == 4'd10)
             begin
                cs <= 1'b1;
                cmd_rdy = 1'b1;
                mosi <= 1'b0;
              end
          end
        W_FINISH  :
        // begin
        //   cs <= 1'b1;
        //   cmd_rdy = 1'b1;
        //   mosi <= 1'b0;
        // end
        ;
        R_START   :
            rbuff <= buff[11:8];
        WR_DATA   :
        begin
            cs <= 1'b0;
            if(clk_cnt == 4'd9)  
              begin
                r_cnt <= r_cnt + 1'b1;
                mosi <= rbuff[w_cnt];
                clk_cnt <= 4'd0; 
                sclk <= ~sclk;
              end
            else if(clk_cnt == 4'd4)
                begin
                    sclk <= ~sclk;
                    clk_cnt <= clk_cnt + 1'b1;
                end
            else 
              begin
              clk_cnt <= clk_cnt + 1'b1;
              mosi <= rbuff[w_cnt];
              end
          end
        R_DELAY:
        begin
            cs <= 1'b1;
            mosi <= 1'b0;
            dly_cnt = dly_cnt + 1'b1;
        end
        RR_DATA   :
          begin
            cs <= 1'b0;
            read_vld <= 1'b1;
            if(clk_cnt == 4'd9)  
              begin
                r_cnt <= r_cnt + 1'b1;
                data_buf <= {data_buf[6:0],miso};
                clk_cnt <= 4'd0; 
                sclk <= ~sclk;
              end
            else if(clk_cnt == 4'd4)
                begin
                sclk <= ~sclk;
                clk_cnt <= clk_cnt + 1'b1;
                end
            else 
              begin
              clk_cnt <= clk_cnt + 1'b1;
              end
          end
        R_FINISH:
          begin
            read_vld = 1'b0;
            cmd_rdy = 1'b1;
          end
    endcase
    
end


endmodule

SPI/SPI_tb.v
`include "SPI.v"
module SPI_tb;

// Parameters
localparam CMD_WIDTH  = 12;
localparam READ_WIDTH = 8 ;

// Ports
reg                   clk       = 0;
reg                   rst_n     = 0;
reg  [ CMD_WIDTH-1:0] cmd_in       ;
wire                  cmd_rdy      ;
reg                   cmd_vld   = 0;
wire                  sclk         ;
wire                  cs           ;
wire                  mosi         ;
reg                   miso      = 0;
wire                  read_vld     ;
wire [READ_WIDTH-1:0] read_data    ;

SPI #(
  .CMD_WIDTH (CMD_WIDTH ),
  .READ_WIDTH(          
              READ_WIDTH)  
) SPI_dut (
  .clk      (clk      ),
  .rst_n    (rst_n    ),
  .cmd_in   (cmd_in   ),
  .cmd_rdy  (cmd_rdy  ),
  .cmd_vld  (cmd_vld  ),
  .sclk     (sclk     ),
  .cs       (cs       ),
  .mosi     (mosi     ),
  .miso     (miso     ),
  .read_vld (read_vld ),
  .read_data(read_data)
);

initial begin
  begin
    #10 rst_n = 1;
    #10 rst_n = 0;
    #20 rst_n = 1;
    #20 wt;
    #100000;
    $finish;
  end
end

always
  #5  clk = ! clk ;
task wt;
  begin
    #10 cmd_in = 12'b1100_1001_0001;
    #10 cmd_vld = 1;
    #20 cmd_vld = 0;
  end
endtask

initial
  begin
    $dumpfile("wave.vcd");        //生成的vcd文件名称
    $dumpvars;
  end

endmodule

SPI/build/wave.vcd
$date
	Thu Mar 17 14:31:33 2022
$end
$version
	Icarus Verilog
$end
$timescale
	1s
$end
$scope module SPI_tb $end
$var wire 1 ! sclk $end
$var wire 1 " read_vld $end
$var wire 8 # read_data [7:0] $end
$var wire 1 $ mosi $end
$var wire 1 % cs $end
$var wire 1 & cmd_rdy $end
$var reg 1 ' clk $end
$var reg 12 ( cmd_in [11:0] $end
$var reg 1 ) cmd_vld $end
$var reg 1 * miso $end
$var reg 1 + rst_n $end
$scope module SPI_dut $end
$var wire 1 ' clk $end
$var wire 12 , cmd_in [11:0] $end
$var wire 1 ) cmd_vld $end
$var wire 1 * miso $end
$var wire 1 - r_start_en $end
$var wire 1 + rst_n $end
$var wire 1 . w_start_en $end
$var wire 1 / work_en $end
$var wire 1 0 w_start_down $end
$var wire 1 1 r_start_down $end
$var reg 12 2 buff [11:0] $end
$var reg 4 3 clk_cnt [3:0] $end
$var reg 1 & cmd_rdy $end
$var reg 1 % cs $end
$var reg 8 4 data_buf [7:0] $end
$var reg 8 5 dly_cnt [7:0] $end
$var reg 4 6 fsm_cs [3:0] $end
$var reg 4 7 fsm_ns [3:0] $end
$var reg 1 $ mosi $end
$var reg 4 8 r_cnt [3:0] $end
$var reg 4 9 rbuff [3:0] $end
$var reg 8 : read_data [7:0] $end
$var reg 1 " read_vld $end
$var reg 1 ! sclk $end
$var reg 4 ; w_cnt [3:0] $end
$upscope $end
$scope task wt $end
$upscope $end
$upscope $end
$enddefinitions $end
#0
$dumpvars
bx ;
bx :
bx 9
bx 8
b0 7
b0 6
bx 5
bx 4
bx 3
bx 2
x1
x0
0/
x.
x-
bx ,
0+
0*
0)
bx (
0'
x&
x%
x$
bx #
x"
x!
$end
#5
0-
0.
b0 #
b0 :
0"
0$
1%
0!
1&
b0 9
b0 4
b0 5
b0 3
b0 2
b0 8
00
01
b0 ;
1'
#10
0'
1+
#15
1'
#20
0'
0+
#25
1'
#30
0'
#35
1'
#40
0'
1+
#45
1'
#50
0'
#55
1'
#60
0'
#65
1'
#70
0'
b110010010001 (
b110010010001 ,
#75
1'
#80
b1 7
0'
1/
1)
#85
b1 6
1'
#90
0'
#95
1.
b11 7
0&
b110010010001 2
1'
#100
b100 7
0'
0/
0)
#105
b100 6
1'
#110
0'
#115
b1 3
1$
0%
1'
#120
0'
#125
b10 3
1'
#130
0'
#135
b11 3
1'
#140
0'
#145
b100 3
1'
#150
0'
#155
b101 3
1'
#160
0'
#165
b110 3
1!
1'
#170
0'
#175
b111 3
1'
#180
0'
#185
b1000 3
1'
#190
0'
#195
b1001 3
1'
#200
0'
#205
b1010 3
b1 ;
1'
#210
0'
#215
0!
b1 3
0$
1'
#220
0'
#225
b10 3
1'
#230
0'
#235
b11 3
1'
#240
0'
#245
b100 3
1'
#250
0'
#255
b101 3
1'
#260
0'
#265
b110 3
1!
1'
#270
0'
#275
b111 3
1'
#280
0'
#285
b1000 3
1'
#290
0'
#295
b1001 3
1'
#300
0'
#305
b1010 3
b10 ;
1'
#310
0'
#315
0!
b1 3
1'
#320
0'
#325
b10 3
1'
#330
0'
#335
b11 3
1'
#340
0'
#345
b100 3
1'
#350
0'
#355
b101 3
1'
#360
0'
#365
b110 3
1!
1'
#370
0'
#375
b111 3
1'
#380
0'
#385
b1000 3
1'
#390
0'
#395
b1001 3
1'
#400
0'
#405
b1010 3
b11 ;
1'
#410
0'
#415
0!
b1 3
1'
#420
0'
#425
b10 3
1'
#430
0'
#435
b11 3
1'
#440
0'
#445
b100 3
1'
#450
0'
#455
b101 3
1'
#460
0'
#465
b110 3
1!
1'
#470
0'
#475
b111 3
1'
#480
0'
#485
b1000 3
1'
#490
0'
#495
b1001 3
1'
#500
0'
#505
b1010 3
b100 ;
1'
#510
0'
#515
0!
b1 3
1$
1'
#520
0'
#525
b10 3
1'
#530
0'
#535
b11 3
1'
#540
0'
#545
b100 3
1'
#550
0'
#555
b101 3
1'
#560
0'
#565
b110 3
1!
1'
#570
0'
#575
b111 3
1'
#580
0'
#585
b1000 3
1'
#590
0'
#595
b1001 3
1'
#600
0'
#605
b1010 3
b101 ;
1'
#610
0'
#615
0!
b1 3
0$
1'
#620
0'
#625
b10 3
1'
#630
0'
#635
b11 3
1'
#640
0'
#645
b100 3
1'
#650
0'
#655
b101 3
1'
#660
0'
#665
b110 3
1!
1'
#670
0'
#675
b111 3
1'
#680
0'
#685
b1000 3
1'
#690
0'
#695
b1001 3
1'
#700
0'
#705
b1010 3
b110 ;
1'
#710
0'
#715
0!
b1 3
1'
#720
0'
#725
b10 3
1'
#730
0'
#735
b11 3
1'
#740
0'
#745
b100 3
1'
#750
0'
#755
b101 3
1'
#760
0'
#765
b110 3
1!
1'
#770
0'
#775
b111 3
1'
#780
0'
#785
b1000 3
1'
#790
0'
#795
b1001 3
1'
#800
0'
#805
b1010 3
b111 ;
1'
#810
0'
#815
0!
b1 3
1$
1'
#820
0'
#825
b10 3
1'
#830
0'
#835
b11 3
1'
#840
0'
#845
b100 3
1'
#850
0'
#855
b101 3
1'
#860
0'
#865
b110 3
1!
1'
#870
0'
#875
b111 3
1'
#880
0'
#885
b1000 3
1'
#890
0'
#895
b1001 3
1'
#900
0'
#905
b1010 3
11
b1000 ;
1'
#910
0'
#915
0!
b1 3
0$
1'
#920
0'
#925
b10 3
1'
#930
0'
#935
b11 3
1'
#940
0'
#945
b100 3
1'
#950
0'
#955
b101 3
1'
#960
0'
#965
b110 3
1!
1'
#970
0'
#975
b111 3
1'
#980
0'
#985
b1000 3
1'
#990
0'
#995
b1001 3
1'
#1000
0'
#1005
b1010 3
01
b1001 ;
1'
#1010
0'
#1015
0!
b1 3
1'
#1020
0'
#1025
b10 3
1'
#1030
0'
#1035
b11 3
1'
#1040
0'
#1045
b100 3
1'
#1050
0'
#1055
b101 3
1'
#1060
0'
#1065
b110 3
1!
1'
#1070
0'
#1075
b111 3
1'
#1080
0'
#1085
b1000 3
1'
#1090
0'
#1095
b1001 3
1'
#1100
0'
#1105
b1010 3
b1010 ;
1'
#1110
0'
#1115
0!
b1 3
1$
1'
#1120
0'
#1125
b10 3
1'
#1130
0'
#1135
b11 3
1'
#1140
0'
#1145
b100 3
1'
#1150
0'
#1155
b101 3
1'
#1160
0'
#1165
b110 3
1!
1'
#1170
0'
#1175
b111 3
1'
#1180
0'
#1185
b1000 3
1'
#1190
0'
#1195
b1001 3
1'
#1200
0'
#1205
b1010 3
b1011 ;
1'
#1210
0'
#1215
0!
b1 3
1'
#1220
0'
#1225
b10 3
1'
#1230
0'
#1235
b11 3
1'
#1240
0'
#1245
b100 3
1'
#1250
0'
#1255
b101 3
1'
#1260
0'
#1265
b110 3
1!
1'
#1270
0'
#1275
b111 3
1'
#1280
0'
#1285
b1000 3
1'
#1290
0'
#1295
b1001 3
1'
#1300
0'
#1305
b101 7
b1010 3
10
b1100 ;
1'
#1310
0'
#1315
1%
0!
b1 3
0$
b101 6
b0 7
0.
1&
1'
#1320
0'
#1325
b0 6
1'
#1330
0'
#1335
b0 3
b0 2
00
b0 ;
1'
