.history/UART/uart1_20220311024511.v
module uart #(
  parameter CMD_WIDTH  = 16    ,
  parameter READ_WIDTH = 8     ,
  parameter BR         = 115200,
  parameter CHEAK      = 1
) (
  input                       clk      ,
  input                       rst_n    ,
  input      [ CMD_WIDTH-1:0] cmd_in   ,
  input                       cmd_vld  ,
  input                       rx       ,
  output reg                  tx       ,
  output                   read_rdy ,
  output     [READ_WIDTH-1:0] read_data,
  output reg                  cmd_rdy
);

  reg                  cmd_rdy_nxt      ;
  reg  [CMD_WIDTH-1:0] cmd_temp         ;
  reg  [         10:0] tx_temp          ;
  reg  [          8:0] br          = 434;
  reg  [          8:0] br_cnt           ;
  reg  [          3:0] tx_cnt           ;
  reg                  tx_flag          ;
  wire                 tx_nxt           ;
  wire                 work_down        ;
  reg                  work_en          ;
  wire                 tx_cnt_en        ;
  wire                 rw_flag          ;
  assign rw_flag = cmd_temp[CMD_WIDTH-1];
//开始信号
  assign work_down = (~rw_flag||tx_flag) && br_cnt ==br && tx_cnt == 10;
  always @(posedge clk or negedge rst_n) begin
    if(!rst_n)
      work_en <= 1'b0;
    else if(work_down)
      work_en <= 1'b0;
    else if(cmd_vld)
      work_en <= 1'b1;
  end
//握手信号
  always @(posedge clk or rst_n) begin
    if(!rst_n)
      cmd_rdy <= 1'b1;
    else if (cmd_vld)
      cmd_rdy <= 1'b0;
    else if(work_down)
      cmd_rdy <= 1'b1;
  end
//暂存数据
  always@(posedge clk or negedge rst_n)
    begin
      if((!rst_n))
        cmd_temp <= {CMD_WIDTH{1'b0}};
      else if(cmd_vld && cmd_rdy)
        cmd_temp <= cmd_in;
    end
//数据分配
  always@(posedge clk or negedge rst_n)
    begin
      if(!rst_n)
        tx_temp <= 0;
      else if(!cmd_vld && !tx_flag)
        tx_temp <= {1'b0,cmd_temp[15:8],~^cmd_temp[15:7],1'b0};
      else if(!cmd_vld && tx_flag)
        tx_temp <= {1'b0,cmd_temp[7:0],~^cmd_temp[7:0],1'b0};
    end

//波特率计数器
  always @(posedge clk or negedge rst_n) begin
    if(!rst_n)
      br_cnt <= 9'b0;
    else if(br_cnt == br)
      br_cnt <= 9'b0;
    else if(work_en && tx_cnt<=10)
      br_cnt <= br_cnt + 1;

  end

//发送计数器
  always @(posedge clk or negedge rst_n) begin
    if(!rst_n)
      tx_cnt <= 4'b0;
    else if (tx_cnt == 11)
      tx_cnt <= 4'b0;
    else if(br_cnt == br)
      tx_cnt <= tx_cnt + 1;
  end

//发送标记
  always @(posedge clk or negedge rst_n) begin
    if(!rst_n)
      tx_flag <= 0;
    else if(tx_cnt == 10 && rw_flag && br_cnt==br)
      tx_flag <= ~tx_flag;
  end

//发送
  always @(posedge clk or negedge rst_n) begin
    if(!rst_n)
      tx <= 0;
    else if(tx_cnt>=1)
      if(br_cnt)
        tx <= tx_temp[10-tx_cnt];
    else if(tx_cnt == 0)
      tx <= 1'b0;
  end

  reg  [2:0] rx_dly      ;
  wire       nedge_rx    ;
  reg        rx_work_en  ;
  reg  [7:0] rx_data_buf ;
  wire       rx_sync     ;
  wire       check_finish;
  reg        rx_work_done;
  reg   [3:0]     rx_cnt      ;
  reg  [8:0]      br_cnt2     ;
  always @(posedge clk or negedge rst_n) begin
    if(!rst_n)
      rx_dly <= 3'b0;
    else
      rx_dly <= {rx_dly[1:0],rx};
  end

  assign nedge_rx = rx_dly[2:1] == 2'b01;

  assign rx_sync  = rx_dly[2];

  always @(posedge clk or negedge rst_n) begin
    if(!rst_n)
      rx_work_en <= 1'b0;
    else if(rx_work_done)
      rx_work_en <= 1'b0;
    else if(nedge_rx)
      rx_work_en <= 1'b1;
  end

//波特率计数器
  always @(posedge clk or negedge rst_n) begin
    if(!rst_n)
      br_cnt2 <= 9'b0;
      else if(br_cnt2 == br)
        br_cnt2 <= 9'b0;
    else if(rx_work_en && rx_cnt<=11)
      br_cnt2 <= br_cnt2 + 1;
    
  end

//发送计数器
  always @(posedge clk or negedge rst_n) begin
    if(!rst_n)
      rx_cnt <= 4'b0;
    else if (rx_cnt == 11)
      rx_cnt <= 4'b0;
    else if(br_cnt == br)
      rx_cnt <= rx_cnt + 1;
  end


  always @(posedge clk or negedge rst_n) begin
    if(!rst_n)
      rx_data_buf <= 8'b0;
    else if (br_cnt2 && rx_work_en)
      if((rx_cnt<9) && br_cnt2 == br/2)
        rx_data_buf <= {rx_data_buf[6:0],rx_sync};
    else 
       rx_data_buf <= 8'b0;
  end

  assign rx_work_down = br_cnt2 == br && rx_cnt == 4'd10;

  assign check_finish = br_cnt2==br/2 && rx_cnt==4'd9 && rx_sync==~^rx_data_buf;

  assign read_rdy = check_finish;

 end

  assign read_data = rx_data_buf ;
endmodule

.history/UART/uart_tb_20220311015158.v
`include "uart1.v"
module uart_tb;

// Parameters
localparam CMD_WIDTH  = 16    ;
localparam READ_WIDTH = 8     ;
localparam BR         = 115200;
localparam CHEAK      = 1     ;
// Ports
reg         clk       = 0;
reg         rst_n     = 0;
reg  [15:0] cmd_in       ;
reg         cmd_vld   = 0;
reg         rx        = 1;
wire        tx           ;
wire        read_rdy     ;
wire [ 7:0] read_data    ;
wire        cmd_rdy      ;

uart #(
  .CMD_WIDTH (CMD_WIDTH ),
  .READ_WIDTH(READ_WIDTH),
  .BR        (BR        ),
  .CHEAK     (CHEAK     )
) uart_dut (
  .clk      (clk      ),
  .rst_n    (rst_n    ),
  .cmd_in   (cmd_in   ),
  .cmd_vld  (cmd_vld  ),
  .rx       (tx_temp       ),
  .tx       (tx       ),
  .read_rdy (read_rdy ),
  .read_data(read_data),
  .cmd_rdy  (cmd_rdy  )
);

wire rx_temp;
assign #100 rx_temp=tx;
initial begin
  begin
    rst_n = 1;
    cmd_vld = 0;
    rx = 1;
    #10 rst_n = 0;
    #10 rst_n = 1;
    #1000000;
    $finish;
  end
end
initial begin
  wt;
  #100;
    //rd;
end
task wt;
  begin
    #100;
    @(posedge clk)
      begin
        cmd_in = 16'b1100110000111111;
      end
    @(posedge clk)
      cmd_vld = 1;
    #100;
    @(posedge clk)
      cmd_vld =0;
      #50
      @(posedge clk)
      begin
        cmd_in = 16'b0;
      end
  end
endtask

/*task rd;
  begin
    #100;
    @(posedge clk)
      rx = 0;
    @(posedge clk)
      rx = 1;
    @(posedge clk)
      rx = 1;
    @(posedge clk)
      rx = 1;
    @(posedge clk)
      rx = 0;
    @(posedge clk)
      rx = 1;
    @(posedge clk)
      rx = 0;
    @(posedge clk)
      rx = 1;
    @(posedge clk)
      rx = 0;
    @(posedge clk)
      rx = 1;
    @(posedge clk)
      rx = 0;
    @(posedge clk)
      rx = 1;
    @(posedge clk)
      rx = 1;
    @(posedge clk)
      rx = 1;
    @(posedge clk)
      rx = 0;
    @(posedge clk)
      rx = 1;
    @(posedge clk)
      rx = 0;
    @(posedge clk)
      rx = 1;
    @(posedge clk)
      rx = 1;
    @(posedge clk)
      rx = 0;


  end
endtask
*/
always
  #5  clk = ! clk ;


initial
  begin
    $dumpfile("wave.vcd");        //生成的vcd文件名称
    $dumpvars;
  end
endmodule

UART/build/wave.vcd
$date
	Fri Mar 11 02:47:38 2022
$end
$version
	Icarus Verilog
$end
$timescale
	1s
$end
$scope module uart_tb $end
$var wire 1 ! rx_temp $end
$var wire 1 " tx $end
$var wire 1 # read_rdy $end
$var wire 8 $ read_data [7:0] $end
$var wire 1 % cmd_rdy $end
$var reg 1 & clk $end
$var reg 16 ' cmd_in [15:0] $end
$var reg 1 ( cmd_vld $end
$var reg 1 ) rst_n $end
$var reg 1 * rx $end
$scope module uart_dut $end
$var wire 1 + check_finish $end
$var wire 1 & clk $end
$var wire 16 , cmd_in [15:0] $end
$var wire 1 ( cmd_vld $end
$var wire 8 - read_data [7:0] $end
$var wire 1 # read_rdy $end
$var wire 1 ) rst_n $end
$var wire 1 ! rx $end
$var wire 1 . rx_work_down $end
$var wire 1 / work_down $end
$var wire 1 0 rx_sync $end
$var wire 1 1 rw_flag $end
$var wire 1 2 nedge_rx $end
$var reg 9 3 br [8:0] $end
$var reg 9 4 br_cnt [8:0] $end
$var reg 9 5 br_cnt2 [8:0] $end
$var reg 1 % cmd_rdy $end
$var reg 16 6 cmd_temp [15:0] $end
$var reg 4 7 rx_cnt [3:0] $end
$var reg 8 8 rx_data_buf [7:0] $end
$var reg 3 9 rx_dly [2:0] $end
$var reg 1 : rx_work_done $end
$var reg 1 ; rx_work_en $end
$var reg 1 " tx $end
$var reg 4 < tx_cnt [3:0] $end
$var reg 1 = tx_flag $end
$var reg 11 > tx_temp [10:0] $end
$var reg 1 ? work_en $end
$upscope $end
$scope task wt $end
$upscope $end
$upscope $end
$enddefinitions $end
#0
$dumpvars
x?
bx >
x=
bx <
x;
x:
bx 9
bx 8
bx 7
bx 6
bx 5
bx 4
b110110010 3
x2
x1
x0
x/
x.
bx -
bx ,
x+
1*
1)
0(
bx '
0&
x%
bx $
x#
x"
x!
$end
#5
1&
#10
0#
0+
01
0/
02
00
0.
0?
b0 6
b0 >
b0 4
b0 <
0=
0"
b0 9
0;
b0 5
b0 7
b0 $
b0 -
b0 8
1%
0&
0)
#15
1&
#20
0&
1)
#25
b10 >
b0x 9
1&
#30
0&
#35
x2
b0xx 9
1&
#40
0&
#45
x0
bx 9
1&
#50
0&
#55
1&
#60
0&
#65
1&
#70
0&
#75
1&
#80
0&
#85
1&
#90
0&
#95
1&
#100
0&
#105
b1100110000111111 '
b1100110000111111 ,
1&
#110
0&
0!
#115
11
bx0 9
b1100110000111111 6
1?
0%
1(
1&
#120
0&
#125
02
b1 4
bx00 9
1&
#130
0&
#135
00
b0 9
b10 4
1&
#140
0&
#145
b11 4
1&
#150
0&
#155
b100 4
1&
#160
0&
#165
b101 4
1&
#170
0&
#175
b110 4
1&
#180
0&
#185
b111 4
1&
#190
0&
#195
b1000 4
1&
#200
0&
#205
b1001 4
1&
#210
0&
#215
b1010 4
b1100110010 >
0(
1&
#220
0&
#225
b1011 4
1&
#230
0&
#235
b1100 4
1&
#240
0&
#245
b1101 4
1&
#250
0&
#255
b1110 4
1&
#260
0&
#265
b1111 4
b0 '
b0 ,
1&
#270
0&
#275
b10000 4
1&
#280
0&
#285
b10001 4
1&
#290
0&
#295
b10010 4
1&
#300
0&
#305
b10011 4
1&
#310
0&
#315
b10100 4
1&
#320
0&
#325
b10101 4
1&
#330
0&
#335
b10110 4
1&
#340
0&
#345
b10111 4
1&
#350
0&
#355
b11000 4
1&
#360
0&
#365
b11001 4
1&
#370
0&
#375
b11010 4
1&
#380
0&
#385
b11011 4
1&
#390
0&
#395
b11100 4
1&
#400
0&
#405
b11101 4
1&
#410
0&
#415
b11110 4
1&
#420
0&
#425
b11111 4
1&
#430
0&
#435
b100000 4
1&
#440
0&
#445
b100001 4
1&
#450
0&
#455
b100010 4
1&
#460
0&
#465
b100011 4
1&
#470
0&
#475
b100100 4
1&
#480
0&
#485
b100101 4
1&
#490
0&
#495
b100110 4
1&
#500
0&
#505
b100111 4
1&
#510
0&
#515
b101000 4
1&
#520
0&
#525
b101001 4
1&
#530
0&
#535
b101010 4
1&
#540
0&
#545
b101011 4
1&
#550
0&
#555
b101100 4
1&
#560
0&
#565
b101101 4
1&
#570
0&
#575
b101110 4
1&
#580
0&
#585
b101111 4
1&
#590
0&
#595
b110000 4
1&
#600
0&
#605
b110001 4
1&
#610
0&
#615
b110010 4
1&
#620
0&
#625
b110011 4
1&
#630
0&
#635
b110100 4
1&
#640
0&
#645
b110101 4
1&
#650
0&
#655
b110110 4
1&
#660
0&
#665
b110111 4
1&
#670
0&
#675
b111000 4
1&
#680
0&
#685
b111001 4
1&
#690
0&
#695
b111010 4
1&
#700
0&
#705
b111011 4
1&
#710
0&
#715
b111100 4
1&
#720
0&
#725
b111101 4
1&
#730
0&
#735
b111110 4
1&
#740
0&
#745
b111111 4
1&
#750
0&
#755
b1000000 4
1&
#760
0&
#765
b1000001 4
1&
#770
0&
#775
b1000010 4
1&
#780
0&
#785
b1000011 4
1&
#790
0&
#795
b1000100 4
1&
#800
0&
#805
b1000101 4
1&
#810
0&
#815
b1000110 4
1&
#820
0&
#825
b1000111 4
1&
#830
0&
#835
b1001000 4
1&
#840
0&
#845
b1001001 4
1&
#850
0&
#855
b1001010 4
1&
#860
0&
#865
b1001011 4
1&
#870
0&
#875
b1001100 4
1&
#880
0&
#885
b1001101 4
1&
#890
0&
#895
b1001110 4
1&
#900
0&
#905
b1001111 4
1&
#910
0&
#915
b1010000 4
1&
#920
0&
#925
b1010001 4
1&
#930
0&
#935
b1010010 4
1&
#940
0&
#945
b1010011 4
1&
#950
0&
#955
b1010100 4
1&
#960
0&
#965
b1010101 4
1&
#970
0&
#975
b1010110 4
1&
#980
0&
#985
b1010111 4
1&
#990
0&
#995
b1011000 4
1&
#1000
0&
#1005
b1011001 4
1&
#1010
0&
#1015
b1011010 4
1&
#1020
0&
#1025
b1011011 4
1&
#1030
0&
#1035
b1011100 4
1&
#1040
0&
#1045
b1011101 4
1&
#1050
0&
#1055
b1011110 4
1&
#1060
0&
#1065
b1011111 4
1&
#1070
0&
#1075
b1100000 4
1&
#1080
0&
#1085
b1100001 4
1&
#1090
0&
#1095
b1100010 4
1&
#1100
0&
#1105
b1100011 4
1&
#1110
0&
#1115
b1100100 4
1&
#1120
0&
#1125
b1100101 4
1&
#1130
0&
#1135
b1100110 4
1&
#1140
0&
#1145
b1100111 4
1&
#1150
0&
#1155
b1101000 4
1&
#1160
0&
#1165
b1101001 4
1&
#1170
0&
#1175
b1101010 4
1&
#1180
0&
#1185
b1101011 4
1&
#1190
0&
#1195
b1101100 4
1&
#1200
0&
#1205
b1101101 4
1&
#1210
0&
#1215
b1101110 4
1&
#1220
0&
#1225
b1101111 4
1&
#1230
0&
#1235
b1110000 4
1&
#1240
0&
#1245
b1110001 4
1&
#1250
0&
#1255
b1110010 4
1&
#1260
0&
#1265
b1110011 4
1&
#1270
0&
#1275
b1110100 4
1&
#1280
0&
#1285
b1110101 4
1&
#1290
0&
#1295
b1110110 4
1&
#1300
0&
#1305
b1110111 4
1&
#1310
0&
#1315
b1111000 4
1&
#1320
0&
#1325
b1111001 4
1&
#1330
0&
#1335
b1111010 4
1&
#1340
0&
#1345
b1111011 4
1&
#1350
0&
#1355
b1111100 4
1&
#1360
0&
#1365
b1111101 4
1&
#1370
0&
#1375
b1111110 4
1&
#1380
0&
#1385
b1111111 4
1&
#1390
0&
#1395
b10000000 4
1&
#1400
0&
#1405
b10000001 4
1&
#1410
0&
#1415
b10000010 4
1&
#1420
0&
#1425
b10000011 4
1&
#1430
0&
#1435
b10000100 4
1&
#1440
0&
#1445
b10000101 4
1&
#1450
0&
#1455
b10000110 4
1&
#1460
0&
#1465
b10000111 4
1&
#1470
0&
#1475
b10001000 4
1&
#1480
0&
#1485
b10001001 4
1&
#1490
0&
#1495
b10001010 4
1&
#1500
0&
#1505
b10001011 4
1&
#1510
0&
#1515
b10001100 4
1&
#1520
0&
#1525
b10001101 4
1&
#1530
0&
#1535
b10001110 4
1&
#1540
0&
#1545
b10001111 4
1&
#1550
0&
#1555
b10010000 4
1&
#1560
0&
#1565
b10010001 4
1&
#1570
0&
#1575
b10010010 4
1&
#1580
0&
#1585
b10010011 4
1&
#1590
0&
#1595
b10010100 4
1&
#1600
0&
#1605
b10010101 4
1&
#1610
0&
#1615
b10010110 4
1&
#1620
0&
#1625
b10010111 4
1&
#1630
0&
#1635
b10011000 4
1&
#1640
0&
#1645
b10011001 4
1&
#1650
0&
#1655
b10011010 4
1&
#1660
0&
#1665
b10011011 4
1&
#1670
0&
#1675
b10011100 4
1&
#1680
0&
#1685
b10011101 4
1&
#1690
0&
#1695
b10011110 4
1&
#1700
0&
#1705
b10011111 4
1&
#1710
0&
#1715
b10100000 4
1&
#1720
0&
#1725
b10100001 4
1&
#1730
0&
#1735
b10100010 4
1&
#1740
0&
#1745
b10100011 4
1&
#1750
0&
#1755
b10100100 4
1&
#1760
0&
#1765
b10100101 4
1&
#1770
0&
#1775
b10100110 4
1&
#1780
0&
#1785
b10100111 4
1&
#1790
0&
#1795
b10101000 4
1&
#1800
0&
#1805
b10101001 4
1&
#1810
0&
#1815
b10101010 4
1&
#1820
0&
#1825
b10101011 4
1&
#1830
0&
#1835
b10101100 4
1&
#1840
0&
#1845
b10101101 4
1&
#1850
0&
#1855
b10101110 4
1&
#1860
0&
#1865
b10101111 4
1&
#1870
0&
#1875
b10110000 4
1&
#1880
0&
#1885
b10110001 4
1&
#1890
0&
#1895
b10110010 4
1&
#1900
0&
#1905
b10110011 4
1&
#1910
0&
#1915
b10110100 4
1&
#1920
0&
#1925
b10110101 4
1&
#1930
0&
#1935
b10110110 4
1&
#1940
0&
#1945
b10110111 4
1&
#1950
0&
#1955
b10111000 4
1&
#1960
0&
#1965
b10111001 4
1&
#1970
0&
#1975
b10111010 4
1&
#1980
0&
#1985
b10111011 4
1&
#1990
0&
#1995
b10111100 4
1&
#2000
0&
#2005
b10111101 4
1&
#2010
0&
#2015
b10111110 4
1&
#2020
0&
#2025
b10111111 4
1&
#2030
0&
#2035
b11000000 4
1&
#2040
0&
#2045
b11000001 4
1&
#2050
0&
#2055
b11000010 4
1&
#2060
0&
#2065
b11000011 4
1&
#2070
0&
#2075
b11000100 4
1&
#2080
0&
#2085
b11000101 4
1&
#2090
0&
#2095
b11000110 4
1&
#2100
0&
#2105
b11000111 4
1&
#2110
0&
#2115
b11001000 4
1&
#2120
0&
#2125
b11001001 4
1&
#2130
0&
#2135
b11001010 4
1&
#2140
0&
#2145
b11001011 4
1&
#2150
0&
#2155
b11001100 4
1&
#2160
0&
#2165
b11001101 4
1&
#2170
0&
#2175
b11001110 4
1&
#2180
0&
#2185
b11001111 4
1&
#2190
0&
#2195
b11010000 4
1&
#2200
0&
#2205
b11010001 4
1&
#2210
0&
#2215
b11010010 4
1&
#2220
0&
#2225
b11010011 4
1&
#2230
0&
#2235
b11010100 4
1&
#2240
0&
#2245
b11010101 4
1&
#2250
0&
#2255
b11010110 4
1&
#2260
0&
#2265
b11010111 4
1&
#2270
0&
#2275
b11011000 4
1&
#2280
0&
#2285
b11011001 4
1&
#2290
0&
#2295
b11011010 4
1&
#2300
0&
#2305
b11011011 4
1&
#2310
0&
#2315
b11011100 4
1&
#2320
0&
#2325
b11011101 4
1&
#2330
0&
#2335
b11011110 4
1&
#2340
0&
#2345
b11011111 4
1&
#2350
0&
#2355
b11100000 4
1&
#2360
0&
#2365
b11100001 4
1&
#2370
0&
#2375
b11100010 4
1&
#2380
0&
#2385
b11100011 4
1&
#2390
0&
#2395
b11100100 4
1&
#2400
0&
#2405
b11100101 4
1&
#2410
0&
#2415
b11100110 4
1&
#2420
0&
#2425
b11100111 4
1&
#2430
0&
#2435
b11101000 4
1&
#2440
0&
#2445
b11101001 4
1&
#2450
0&
#2455
b11101010 4
1&
#2460
0&
#2465
b11101011 4
1&
#2470
0&
#2475
b11101100 4
1&
#2480
0&
#2485
b11101101 4
1&
#2490
0&
#2495
b11101110 4
1&
#2500
0&
#2505
b11101111 4
1&
#2510
0&
#2515
b11110000 4
1&
#2520
0&
#2525
b11110001 4
1&
#2530
0&
#2535
b11110010 4
1&
#2540
0&
#2545
b11110011 4
1&
#2550
0&
#2555
b11110100 4
1&
#2560
0&
#2565
b11110101 4
1&
#2570
0&
#2575
b11110110 4
1&
#2580
0&
#2585
b11110111 4
1&
#2590
0&
#2595
b11111000 4
1&
#2600
0&
#2605
b11111001 4
1&
#2610
0&
#2615
b11111010 4
1&
#2620
0&
#2625
b11111011 4
1&
#2630
0&
#2635
b11111100 4
1&
#2640
0&
#2645
b11111101 4
1&
#2650
0&
#2655
b11111110 4
1&
#2660
0&
#2665
b11111111 4
1&
#2670
0&
#2675
b100000000 4
1&
#2680
0&
#2685
b100000001 4
1&
#2690
0&
#2695
b100000010 4
1&
#2700
0&
#2705
b100000011 4
1&
#2710
0&
#2715
b100000100 4
1&
#2720
0&
#2725
b100000101 4
1&
#2730
0&
#2735
b100000110 4
1&
#2740
0&
#2745
b100000111 4
1&
#2750
0&
#2755
b100001000 4
1&
#2760
0&
#2765
b100001001 4
1&
#2770
0&
#2775
b100001010 4
1&
#2780
0&
#2785
b100001011 4
1&
#2790
0&
#2795
b100001100 4
1&
#2800
0&
#2805
b100001101 4
1&
#2810
0&
#2815
b100001110 4
1&
#2820
0&
#2825
b100001111 4
1&
#2830
0&
#2835
b100010000 4
1&
#2840
0&
#2845
b100010001 4
1&
#2850
0&
#2855
b100010010 4
1&
#2860
0&
#2865
b100010011 4
1&
#2870
0&
#2875
b100010100 4
1&
#2880
0&
#2885
b100010101 4
1&
#2890
0&
#2895
b100010110 4
1&
#2900
0&
#2905
b100010111 4
1&
#2910
0&
#2915
b100011000 4
1&
#2920
0&
#2925
b100011001 4
1&
#2930
0&
#2935
b100011010 4
1&
#2940
0&
#2945
b100011011 4
1&
#2950
0&
#2955
b100011100 4
1&
#2960
0&
#2965
b100011101 4
1&
#2970
0&
#2975
b100011110 4
1&
#2980
0&
#2985
b100011111 4
1&
#2990
0&
#2995
b100100000 4
1&
#3000
0&
#3005
b100100001 4
1&
#3010
0&
#3015
b100100010 4
1&
#3020
0&
#3025
b100100011 4
1&
#3030
0&
#3035
b100100100 4
1&
#3040
0&
#3045
b100100101 4
1&
#3050
0&
#3055
b100100110 4
1&
#3060
0&
#3065
b100100111 4
1&
#3070
0&
#3075
b100101000 4
1&
#3080
0&
#3085
b100101001 4
1&
#3090
0&
#3095
b100101010 4
1&
#3100
0&
#3105
b100101011 4
1&
#3110
0&
#3115
b100101100 4
1&
#3120
0&
#3125
b100101101 4
1&
#3130
0&
#3135
b100101110 4
1&
#3140
0&
#3145
b100101111 4
1&
#3150
0&
#3155
b100110000 4
1&
#3160
0&
#3165
b100110001 4
1&
#3170
0&
#3175
b100110010 4
1&
#3180
0&
#3185
b100110011 4
1&
#3190
0&
#3195
b100110100 4
1&
#3200
0&
#3205
b100110101 4
1&
#3210
0&
#3215
b100110110 4
1&
#3220
0&
#3225
b100110111 4
1&
#3230
0&
#3235
b100111000 4
1&
#3240
0&
#3245
b100111001 4
1&
#3250
0&
#3255
b100111010 4
1&
#3260
0&
#3265
b100111011 4
1&
#3270
0&
#3275
b100111100 4
1&
#3280
0&
#3285
b100111101 4
1&
#3290
0&
#3295
b100111110 4
1&
#3300
0&
#3305
b100111111 4
1&
#3310
0&
#3315
b101000000 4
1&
#3320
0&
#3325
b101000001 4
1&
#3330
0&
#3335
b101000010 4
1&
#3340
0&
#3345
b101000011 4
1&
#3350
0&
#3355
b101000100 4
1&
#3360
0&
#3365
b101000101 4
1&
#3370
0&
#3375
b101000110 4
1&
#3380
0&
#3385
b101000111 4
1&
#3390
0&
#3395
b101001000 4
1&
#3400
0&
#3405
b101001001 4
1&
#3410
0&
#3415
b101001010 4
1&
#3420
0&
#3425
b101001011 4
1&
#3430
0&
#3435
b101001100 4
1&
#3440
0&
#3445
b101001101 4
1&
#3450
0&
#3455
b101001110 4
1&
#3460
0&
#3465
b101001111 4
1&
#3470
0&
#3475
b101010000 4
1&
#3480
0&
#3485
b101010001 4
1&
#3490
0&
#3495
b101010010 4
1&
#3500
0&
#3505
b101010011 4
1&
#3510
0&
#3515
b101010100 4
1&
#3520
0&
#3525
b101010101 4
1&
#3530
0&
#3535
b101010110 4
1&
#3540
0&
#3545
b101010111 4
1&
#3550
0&
#3555
b101011000 4
1&
#3560
0&
#3565
b101011001 4
1&
#3570
0&
#3575
b101011010 4
1&
#3580
0&
#3585
b101011011 4
1&
#3590
0&
#3595
b101011100 4
1&
#3600
0&
#3605
b101011101 4
1&
#3610
0&
#3615
b101011110 4
1&
#3620
0&
#3625
b101011111 4
1&
#3630
0&
#3635
b101100000 4
1&
#3640
0&
#3645
b101100001 4
1&
#3650
0&
#3655
b101100010 4
1&
#3660
0&
#3665
b101100011 4
1&
#3670
0&
#3675
b101100100 4
1&
#3680
0&
#3685
b101100101 4
1&
#3690
0&
#3695
b101100110 4
1&
#3700
0&
#3705
b101100111 4
1&
#3710
0&
#3715
b101101000 4
1&
#3720
0&
#3725
b101101001 4
1&
#3730
0&
#3735
b101101010 4
1&
#3740
0&
#3745
b101101011 4
1&
#3750
0&
#3755
b101101100 4
1&
#3760
0&
#3765
b101101101 4
1&
#3770
0&
#3775
b101101110 4
1&
#3780
0&
#3785
b101101111 4
1&
#3790
0&
#3795
b101110000 4
1&
#3800
0&
#3805
b101110001 4
1&
#3810
0&
#3815
b101110010 4
1&
#3820
0&
#3825
b101110011 4
1&
#3830
0&
#3835
b101110100 4
1&
#3840
0&
#3845
b101110101 4
1&
#3850
0&
#3855
b101110110 4
1&
#3860
0&
#3865
b101110111 4
1&
#3870
0&
#3875
b101111000 4
1&
#3880
0&
#3885
b101111001 4
1&
#3890
0&
#3895
b101111010 4
1&
#3900
0&
#3905
b101111011 4
1&
#3910
0&
#3915
b101111100 4
1&
#3920
0&
#3925
b101111101 4
1&
#3930
0&
#3935
b101111110 4
1&
#3940
0&
#3945
b101111111 4
1&
#3950
0&
#3955
b110000000 4
1&
#3960
0&
#3965
b110000001 4
1&
#3970
0&
#3975
b110000010 4
1&
#3980
0&
#3985
b110000011 4
1&
#3990
0&
#3995
b110000100 4
1&
#4000
0&
#4005
b110000101 4
1&
#4010
0&
#4015
b110000110 4
1&
#4020
0&
#4025
b110000111 4
1&
#4030
0&
#4035
b110001000 4
1&
#4040
0&
#4045
b110001001 4
1&
#4050
0&
#4055
b110001010 4
1&
#4060
0&
#4065
b110001011 4
1&
#4070
0&
#4075
b110001100 4
1&
#4080
0&
#4085
b110001101 4
1&
#4090
0&
#4095
b110001110 4
1&
#4100
0&
#4105
b110001111 4
1&
#4110
0&
#4115
b110010000 4
1&
#4120
0&
#4125
b110010001 4
1&
#4130
0&
#4135
b110010010 4
1&
#4140
0&
#4145
b110010011 4
1&
#4150
0&
#4155
b110010100 4
1&
#4160
0&
#4165
b110010101 4
1&
#4170
0&
#4175
b110010110 4
1&
#4180
0&
#4185
b110010111 4
1&
#4190
0&
#4195
b110011000 4
1&
#4200
0&
#4205
b110011001 4
1&
#4210
0&
#4215
b110011010 4
1&
#4220
0&
#4225
b110011011 4
1&
#4230
0&
#4235
b110011100 4
1&
#4240
0&
#4245
b110011101 4
1&
#4250
0&
#4255
b110011110 4
1&
#4260
0&
#4265
b110011111 4
1&
#4270
0&
#4275
b110100000 4
1&
#4280
0&
#4285
b110100001 4
1&
#4290
0&
#4295
b110100010 4
1&
#4300
0&
#4305
b110100011 4
1&
#4310
0&
#4315
b110100100 4
1&
#4320
0&
#4325
b110100101 4
1&
#4330
0&
#4335
b110100110 4
1&
#4340
0&
#4345
b110100111 4
1&
#4350
0&
#4355
b110101000 4
1&
#4360
0&
#4365
b110101001 4
1&
#4370
0&
#4375
b110101010 4
1&
#4380
0&
#4385
b110101011 4
1&
#4390
0&
#4395
b110101100 4
1&
#4400
0&
#4405
b110101101 4
1&
#4410
0&
#4415
b110101110 4
1&
#4420
0&
#4425
b110101111 4
1&
#4430
0&
#4435
b110110000 4
1&
#4440
0&
#4445
b110110001 4
1&
#4450
0&
#4455
b110110010 4
1&
#4460
0&
#4465
b0 4
b1 <
b1 7
1&
#4470
0&
#4475
b1 4
1&
#4480
0&
#4485
b10 4
1"
1&
#4490
0&
#4495
b11 4
1&
#4500
0&
#4505
b100 4
1&
#4510
0&
#4515
b101 4
1&
#4520
0&
#4525
b110 4
1&
#4530
0&
#4535
b111 4
1&
#4540
0&
#4545
b1000 4
1&
#4550
0&
#4555
b1001 4
1&
#4560
0&
#4565
b1010 4
1&
#4570
0&
#4575
b1011 4
1&
#4580
0&
#4585
b1100 4
b1 9
1&
1!
#4590
0&
#4595
12
b11 9
b1101 4
1&
#4600
0&
#4605
02
10
b1110 4
b111 9
1;
1&
#4610
0&
#4615
b1 5
b1111 4
1&
#4620
0&
#4625
b10000 4
b10 5
1&
#4630
0&
#4635
b11 5
b10001 4
1&
#4640
0&
#4645
b10010 4
b100 5
1&
#4650
0&
#4655
b101 5
b10011 4
1&
#4660
0&
#4665
b10100 4
b110 5
1&
#4670
0&
#4675
b111 5
b10101 4
1&
#4680
0&
#4685
b10110 4
b1000 5
1&
#4690
0&
#4695
b1001 5
b10111 4
1&
#4700
0&
#4705
b11000 4
b1010 5
1&
#4710
0&
#4715
b1011 5
b11001 4
1&
#4720
0&
#4725
b11010 4
b1100 5
1&
#4730
0&
#4735
b1101 5
b11011 4
1&
#4740
0&
#4745
b11100 4
b1110 5
1&
#4750
0&
#4755
b1111 5
b11101 4
1&
#4760
0&
#4765
b11110 4
b10000 5
1&
#4770
0&
#4775
b10001 5
b11111 4
1&
#4780
0&
#4785
b100000 4
b10010 5
1&
#4790
0&
#4795
b10011 5
b100001 4
1&
#4800
0&
#4805
b100010 4
b10100 5
1&
#4810
0&
#4815
b10101 5
b100011 4
1&
#4820
0&
#4825
b100100 4
b10110 5
1&
#4830
0&
#4835
b10111 5
b100101 4
1&
#4840
0&
#4845
b100110 4
b11000 5
1&
#4850
0&
#4855
b11001 5
b100111 4
1&
#4860
0&
#4865
b101000 4
b11010 5
1&
#4870
0&
#4875
b11011 5
b101001 4
1&
#4880
0&
#4885
b101010 4
b11100 5
1&
#4890
0&
#4895
b11101 5
b101011 4
1&
#4900
0&
#4905
b101100 4
b11110 5
1&
#4910
0&
#4915
b11111 5
b101101 4
1&
#4920
0&
#4925
b101110 4
b100000 5
1&
#4930
0&
#4935
b100001 5
b101111 4
1&
#4940
0&
#4945
b110000 4
b100010 5
1&
#4950
0&
#4955
b100011 5
b110001 4
1&
#4960
0&
#4965
b110010 4
b100100 5
1&
#4970
0&
#4975
b100101 5
b110011 4
1&
#4980
0&
