CRC/CRCCYC.v
module CRCCYC(Clock,Data_In,CRC_En,CRC_Clr,CRC_Out);
input Clock,CRC_En,CRC_Clr;
input [31:0] Data_In;
output [9:0] CRC_Out;
reg [9:0] CRC_Temp;
reg crcfb;
integer i;
always @(posedge Clock) begin
    if(CRC_Clr)
        begin
          CRC_Temp=0;
        end
    else if(CRC_En)
        begin
          for(i=31;i>=0;i=i-1)
          begin
            crcfb = CRC_Temp[9];
            CRC_Temp[9] = CRC_Temp[8]^crcfb;
            CRC_Temp[8] = CRC_Temp[7];
            CRC_Temp[7] = CRC_Temp[6];
            CRC_Temp[6] = CRC_Temp[5];
            CRC_Temp[5] = CRC_Temp[4]^crcfb;
            CRC_Temp[4] = CRC_Temp[3]^crcfb;
            CRC_Temp[3] = CRC_Temp[2];
            CRC_Temp[2] = CRC_Temp[1];
            CRC_Temp[1] = CRC_Temp[0]^crcfb;
            CRC_Temp[0] = Data_In[i]^crcfb;
          end
        end 
end 
assign CRC_Out = CRC_Temp;
endmodule

CRC/Crc_test.v
`timescale 1ns / 1ps
`include "Crc.v"
module test();
reg clk;
reg [31:0] Data_In;
reg CRC_En;
reg CRC_Clr;
wire [9:0] CRC_Out;
initial begin
    clk=0;
    Data_In=32'b1100_0001_0001_1111_1100_0001_1111_0101;
    #5 CRC_En=0;
       CRC_Clr=1;
    #10 CRC_Clr=0;
    #100 CRC_En=1;
    #1000 $finish;
end
always #5 clk=~clk;
CRCCYC Crc(.Clock(clk),
        .Data_In(Data_In),
        .CRC_En(CRC_En),
        .CRC_Clr(CRC_Clr),
        .CRC_Out(CRC_Out));

/*iverilog */
initial
begin            
    $dumpfile("wave.vcd");        //生成的vcd文件名称
    $dumpvars(0, test);     //tb模块名称
end
/*iverilog */
endmodule

CRC/wave.vcd
$date
	Wed Mar  2 01:15:50 2022
$end
$version
	Icarus Verilog
$end
$timescale
	1ps
$end
$scope module test $end
$var wire 10 ! CRC_Out [9:0] $end
$var reg 1 " CRC_Clr $end
$var reg 1 # CRC_En $end
$var reg 32 $ Data_In [31:0] $end
$var reg 1 % clk $end
$scope module Crc $end
$var wire 1 " CRC_Clr $end
$var wire 1 # CRC_En $end
$var wire 10 & CRC_Out [9:0] $end
$var wire 1 % Clock $end
$var wire 32 ' Data_In [31:0] $end
$var reg 10 ( CRC_Temp [9:0] $end
$var reg 1 ) crcfb $end
$var integer 32 * i [31:0] $end
$upscope $end
$upscope $end
$enddefinitions $end
#0
$dumpvars
bx *
x)
bx (
b11000001000111111100000111110101 '
bx &
0%
b11000001000111111100000111110101 $
x#
x"
bx !
$end
#5000
b0 !
b0 &
b0 (
1%
1"
0#
#10000
0%
#15000
1%
0"
#20000
0%
#25000
1%
#30000
0%
#35000
1%
#40000
0%
#45000
1%
#50000
0%
#55000
1%
#60000
0%
#65000
1%
#70000
0%
#75000
1%
#80000
0%
#85000
1%
#90000
0%
#95000
1%
#100000
0%
#105000
1%
#110000
0%
#115000
b1011101 !
b1011101 &
b1011101 (
0)
b11111111111111111111111111111111 *
1%
1#
#120000
0%
#125000
0)
b11101011 !
b11101011 &
b11101011 (
b11111111111111111111111111111111 *
1%
#130000
0%
#135000
1)
b1011000 !
b1011000 &
b1011000 (
b11111111111111111111111111111111 *
1%
#140000
0%
#145000
b1011100110 !
b1011100110 &
b1011100110 (
1)
b11111111111111111111111111111111 *
1%
#150000
0%
#155000
1)
b101000010 !
b101000010 &
b101000010 (
b11111111111111111111111111111111 *
1%
#160000
0%
#165000
b111100 !
b111100 &
b111100 (
1)
b11111111111111111111111111111111 *
1%
#170000
0%
#175000
b11001101 !
b11001101 &
b11001101 (
0)
b11111111111111111111111111111111 *
1%
#180000
0%
#185000
0)
b110101 !
b110101 &
b110101 (
b11111111111111111111111111111111 *
1%
#190000
0%
#195000
0)
b1100011111 !
b1100011111 &
b1100011111 (
b11111111111111111111111111111111 *
1%
#200000
0%
#205000
b1011110111 !
b1011110111 &
b1011110111 (
0)
b11111111111111111111111111111111 *
1%
#210000
0%
#215000
b100101110 !
b100101110 &
b100101110 (
1)
b11111111111111111111111111111111 *
1%
#220000
0%
#225000
b1101111101 !
b1101111101 &
b1101111101 (
0)
b11111111111111111111111111111111 *
1%
#230000
0%
#235000
b1100101010 !
b1100101010 &
b1100101010 (
1)
b11111111111111111111111111111111 *
1%
#240000
0%
#245000
0)
b110110101 !
b110110101 &
b110110101 (
b11111111111111111111111111111111 *
1%
#250000
0%
#255000
1)
b1100110010 !
b1100110010 &
b1100110010 (
b11111111111111111111111111111111 *
1%
#260000
0%
#265000
0)
b1000001011 !
b1000001011 &
b1000001011 (
b11111111111111111111111111111111 *
1%
#270000
0%
#275000
b1010110001 !
b1010110001 &
b1010110001 (
0)
b11111111111111111111111111111111 *
1%
#280000
0%
#285000
b1111011101 !
b1111011101 &
b1111011101 (
0)
b11111111111111111111111111111111 *
1%
#290000
0%
#295000
b1010111011 !
b1010111011 &
b1010111011 (
0)
b11111111111111111111111111111111 *
1%
#300000
0%
#305000
b111110100 !
b111110100 &
b111110100 (
1)
b11111111111111111111111111111111 *
1%
#310000
0%
#315000
b10001111 !
b10001111 &
b10001111 (
0)
b11111111111111111111111111111111 *
1%
#320000
0%
#325000
0)
b1001110011 !
b1001110011 &
b1001110011 (
b11111111111111111111111111111111 *
1%
#330000
0%
#335000
b1110010001 !
b1110010001 &
b1110010001 (
0)
b11111111111111111111111111111111 *
1%
#340000
0%
#345000
b1001100001 !
b1001100001 &
b1001100001 (
0)
b11111111111111111111111111111111 *
1%
#350000
0%
#355000
b1000000110 !
b1000000110 &
b1000000110 (
1)
b11111111111111111111111111111111 *
1%
#360000
0%
#365000
1)
b111010110 !
b111010110 &
b111010110 (
b11111111111111111111111111111111 *
1%
#370000
0%
#375000
b1010111 !
b1010111 &
b1010111 (
0)
b11111111111111111111111111111111 *
1%
#380000
0%
#385000
1)
b1011000010 !
b1011000010 &
b1011000010 (
b11111111111111111111111111111111 *
1%
#390000
0%
#395000
1)
b1001101100 !
b1001101100 &
b1001101100 (
b11111111111111111111111111111111 *
1%
#400000
0%
#405000
0)
b101100001 !
b101100001 &
b101100001 (
b11111111111111111111111111111111 *
1%
#410000
0%
#415000
1)
b1001011100 !
b1001011100 &
b1001011100 (
b11111111111111111111111111111111 *
1%
#420000
0%
#425000
1)
b101110 !
b101110 &
b101110 (
b11111111111111111111111111111111 *
1%
#430000
0%
#435000
b101011010 !
b101011010 &
b101011010 (
1)
b11111111111111111111111111111111 *
1%
#440000
0%
#445000
b1110000010 !
b1110000010 &
b1110000010 (
1)
b11111111111111111111111111111111 *
1%
#450000
0%
#455000
1)
b101001110 !
b101001110 &
b101001110 (
b11111111111111111111111111111111 *
1%
#460000
0%
#465000
b111100011 !
b111100011 &
b111100011 (
0)
b11111111111111111111111111111111 *
1%
#470000
0%
#475000
0)
b1100010101 !
b1100010101 &
b1100010101 (
b11111111111111111111111111111111 *
1%
#480000
0%
#485000
b11011110 !
b11011110 &
b11011110 (
1)
b11111111111111111111111111111111 *
1%
#490000
0%
#495000
b1100011010 !
b1100011010 &
b1100011010 (
1)
b11111111111111111111111111111111 *
1%
#500000
0%
#505000
1)
b11111010 !
b11111010 &
b11111010 (
b11111111111111111111111111111111 *
1%
#510000
0%
#515000
b110100 !
b110100 &
b110100 (
1)
b11111111111111111111111111111111 *
1%
#520000
0%
#525000
b110100111 !
b110100111 &
b110100111 (
0)
b11111111111111111111111111111111 *
1%
#530000
0%
#535000
0)
b1010100101 !
b1010100101 &
b1010100101 (
b11111111111111111111111111111111 *
1%
#540000
0%
#545000
b110111100 !
b110111100 &
b110111100 (
1)
b11111111111111111111111111111111 *
1%
#550000
0%
#555000
b11100000 !
b11100000 &
b11100000 (
1)
b11111111111111111111111111111111 *
1%
#560000
0%
#565000
b11001001 !
b11001001 &
b11001001 (
0)
b11111111111111111111111111111111 *
1%
#570000
0%
#575000
1)
b10000000 !
b10000000 &
b10000000 (
b11111111111111111111111111111111 *
1%
#580000
0%
#585000
b1001010111 !
b1001010111 &
b1001010111 (
0)
b11111111111111111111111111111111 *
1%
#590000
0%
#595000
b10111111 !
b10111111 &
b10111111 (
0)
b11111111111111111111111111111111 *
1%
#600000
0%
#605000
1)
b1100111100 !
b1100111100 &
b1100111100 (
b11111111111111111111111111111111 *
1%
#610000
0%
#615000
0)
b10010111 !
b10010111 &
b10010111 (
b11111111111111111111111111111111 *
1%
#620000
0%
#625000
0)
b111001101 !
b111001101 &
b111001101 (
b11111111111111111111111111111111 *
1%
#630000
0%
#635000
1)
b1000010010 !
b1000010010 &
b1000010010 (
b11111111111111111111111111111111 *
1%
#640000
0%
#645000
0)
b1110110111 !
b1110110111 &
b1110110111 (
b11111111111111111111111111111111 *
1%
#650000
0%
#655000
b1000001100 !
b1000001100 &
b1000001100 (
1)
b11111111111111111111111111111111 *
1%
#660000
0%
#665000
0)
b1111111111 !
b1111111111 &
b1111111111 (
b11111111111111111111111111111111 *
1%
#670000
0%
#675000
b1001100011 !
b1001100011 &
b1001100011 (
0)
b11111111111111111111111111111111 *
1%
#680000
0%
#685000
b101000101 !
b101000101 &
b101000101 (
0)
b11111111111111111111111111111111 *
1%
#690000
0%
#695000
1)
b101110010 !
b101110010 &
b101110010 (
b11111111111111111111111111111111 *
1%
#700000
0%
#705000
b101110011 !
b101110011 &
b101110011 (
0)
b11111111111111111111111111111111 *
1%
#710000
0%
#715000
0)
b1111001011 !
b1111001011 &
b1111001011 (
b11111111111111111111111111111111 *
1%
#720000
0%
#725000
b1110011001 !
b1110011001 &
b1110011001 (
0)
b11111111111111111111111111111111 *
1%
#730000
0%
#735000
b1100001011 !
b1100001011 &
b1100001011 (
0)
b11111111111111111111111111111111 *
1%
#740000
0%
#745000
b10010110 !
b10010110 &
b10010110 (
1)
b11111111111111111111111111111111 *
1%
#750000
0%
#755000
b1101110101 !
b1101110101 &
b1101110101 (
0)
b11111111111111111111111111111111 *
1%
#760000
0%
#765000
b1001000000 !
b1001000000 &
b1001000000 (
1)
b11111111111111111111111111111111 *
1%
#770000
0%
#775000
0)
b1100100101 !
b1100100101 &
b1100100101 (
b11111111111111111111111111111111 *
1%
#780000
0%
#785000
b110010001 !
b110010001 &
b110010001 (
0)
b11111111111111111111111111111111 *
1%
#790000
0%
#795000
1)
b11100 !
b11100 &
b11100 (
b11111111111111111111111111111111 *
1%
#800000
0%
#805000
b1101010110 !
b1101010110 &
b1101010110 (
1)
b11111111111111111111111111111111 *
1%
#810000
0%
#815000
1)
b100000 !
b100000 &
b100000 (
b11111111111111111111111111111111 *
1%
#820000
0%
#825000
b1111000110 !
b1111000110 &
b1111000110 (
1)
b11111111111111111111111111111111 *
1%
#830000
0%
#835000
1)
b11111110 !
b11111110 &
b11111110 (
b11111111111111111111111111111111 *
1%
#840000
0%
#845000
b10000001 !
b10000001 &
b10000001 (
0)
b11111111111111111111111111111111 *
1%
#850000
0%
#855000
0)
b11101111 !
b11101111 &
b11101111 (
b11111111111111111111111111111111 *
1%
#860000
0%
#865000
0)
b11101101 !
b11101101 &
b11101101 (
b11111111111111111111111111111111 *
1%
#870000
0%
#875000
1)
b1110101110 !
b1110101110 &
b1110101110 (
b11111111111111111111111111111111 *
1%
#880000
0%
#885000
1)
b1100001010 !
b1100001010 &
b1100001010 (
b11111111111111111111111111111111 *
1%
#890000
0%
#895000
1)
b1000101110 !
b1000101110 &
b1000101110 (
b11111111111111111111111111111111 *
1%
#900000
0%
#905000
0)
b1100100111 !
b1100100111 &
b1100100111 (
b11111111111111111111111111111111 *
1%
#910000
0%
#915000
b1011010010 !
b1011010010 &
b1011010010 (
1)
b11111111111111111111111111111111 *
1%
#920000
0%
#925000
1)
b10111000 !
b10111000 &
b10111000 (
b11111111111111111111111111111111 *
1%
#930000
0%
#935000
b1001110010 !
b1001110010 &
b1001110010 (
1)
b11111111111111111111111111111111 *
1%
#940000
0%
#945000
0)
b100101001 !
b100101001 &
b100101001 (
b11111111111111111111111111111111 *
1%
#950000
0%
#955000
0)
b1000110011 !
b1000110011 &
b1000110011 (
b11111111111111111111111111111111 *
1%
#960000
0%
#965000
b1010010100 !
b1010010100 &
b1010010100 (
1)
b11111111111111111111111111111111 *
1%
#970000
0%
#975000
0)
b1001001011 !
b1001001011 &
b1001001011 (
b11111111111111111111111111111111 *
1%
#980000
0%
#985000
b1110110100 !
b1110110100 &
b1110110100 (
1)
b11111111111111111111111111111111 *
1%
#990000
0%
#995000
0)
b1111110111 !
b1111110111 &
b1111110111 (
b11111111111111111111111111111111 *
1%
#1000000
0%
#1005000
b1100001001 !
b1100001001 &
b1100001001 (
0)
b11111111111111111111111111111111 *
1%
#1010000
0%
#1015000
b1111010101 !
b1111010101 &
b1111010101 (
0)
b11111111111111111111111111111111 *
1%
#1020000
0%
#1025000
b1111010001 !
b1111010001 &
b1111010001 (
0)
b11111111111111111111111111111111 *
1%
#1030000
0%
#1035000
b1101100100 !
b1101100100 &
b1101100100 (
1)
b11111111111111111111111111111111 *
1%
#1040000
0%
#1045000
1)
b1000101100 !
b1000101100 &
b1000101100 (
b11111111111111111111111111111111 *
1%
#1050000
0%
#1055000
1)
b1100100 !
b1100100 &
b1100100 (
b11111111111111111111111111111111 *
1%
#1060000
0%
#1065000
b1001110110 !
b1001110110 &
b1001110110 (
1)
b11111111111111111111111111111111 *
1%
#1070000
0%
#1075000
1)
b110011100 !
b110011100 &
b110011100 (
b11111111111111111111111111111111 *
1%
#1080000
0%
#1085000
b1101111011 !
b1101111011 &
b1101111011 (
0)
b11111111111111111111111111111111 *
1%
#1090000
0%
#1095000
b11011100 !
b11011100 &
b11011100 (
1)
b11111111111111111111111111111111 *
1%
#1100000
0%
#1105000
b1011001 !
b1011001 &
b1011001 (
0)
b11111111111111111111111111111111 *
1%
#1110000
0%
#1115000
1)
b1011110 !
b1011110 &
b1011110 (
b11111111111111111111111111111111 *
1%
